{
    "priya": {
        "cache": {
            "file": [
                {
                    "read": true,
                    "mtime": 1544196397,
                    "url": "\/mnt\/c\/Library\/Server\/Vendor\/Priya\/Data\/Route.json"
                },
                {
                    "read": true,
                    "mtime": 1530042025,
                    "url": "\/mnt\/c\/Library\/Server\/Vendor\/Priya.System\/Data\/Route.json"
                },
                {
                    "read": true,
                    "mtime": 1511708599,
                    "url": "\/mnt\/c\/Library\/Server\/Vendor\/Priya.Gui\/Data\/Route.json"
                },
                {
                    "read": true,
                    "mtime": 1511708796,
                    "url": "\/mnt\/c\/Library\/Server\/Vendor\/Speak\/Data\/Route.json"
                },
                {
                    "read": true,
                    "mtime": 1549054126,
                    "url": "\/mnt\/c\/Library\/Server\/Vendor\/App\/Data\/Route.json"
                },
                {
                    "read": true,
                    "mtime": 1528741202,
                    "url": "\/mnt\/c\/Library\/Server\/Host\/Documentation\/Priya\/Software\/Data\/Route.json"
                },
                {
                    "read": true,
                    "mtime": 1527717362,
                    "url": "\/mnt\/c\/Library\/Server\/Host\/Priya\/Software\/Data\/Route.json"
                },
                {
                    "read": true,
                    "mtime": 1548679065,
                    "url": "\/mnt\/c\/Library\/Server\/Host\/Redirect\/Data\/Route.json"
                },
                {
                    "read": true,
                    "mtime": 1526130244,
                    "url": "\/mnt\/c\/Library\/Server\/Vendor\/App\/Issue\/Data\/Route.json"
                },
                {
                    "read": true,
                    "mtime": 1530213576,
                    "url": "\/mnt\/c\/Library\/Server\/Vendor\/App\/File\/Manager\/Data\/Route.json"
                },
                {
                    "read": true,
                    "mtime": 1549053330,
                    "url": "\/mnt\/c\/Library\/Server\/Vendor\/App\/Audio\/Player\/Data\/Route.json"
                },
                {
                    "read": true,
                    "mtime": 1514416994,
                    "url": "\/mnt\/c\/Library\/Server\/Vendor\/App\/Youtube\/Data\/Route.json"
                }
            ]
        },
        "route": {
            "cache": {
                "time": {
                    "start": 1549060930.440359,
                    "duration": 0.15123295783996582
                }
            }
        }
    },
    "route": {
        "Indent": {
            "path": "Priya\/Module\/Indent\/Public\/Css\/Indent.css",
            "controller": "Priya.Module.Indent.css",
            "format": "html",
            "language": "en",
            "method": [
                "GET",
                "POST"
            ],
            "translate": false
        },
        "Javascript-CLi": {
            "path": "Javascript",
            "controller": "Priya.Module.Javascript.Cli.run",
            "format": "html",
            "language": "en",
            "method": [
                "CLI"
            ],
            "translate": false
        },
        "Zip-CLi": {
            "path": "Zip",
            "controller": "Priya.Module.File.Zip.Cli.run",
            "format": "html",
            "language": "en",
            "method": [
                "CLI"
            ],
            "translate": false
        },
        "Memory-CLi": {
            "path": "Memory",
            "controller": "Priya.Module.Memory.Cli.run",
            "format": "html",
            "language": "en",
            "method": [
                "CLI"
            ],
            "translate": false
        },
        "system": {
            "path": "System",
            "default": {
                "controller": "Priya.System.run",
                "format": "html",
                "language": "en"
            },
            "method": [
                "CLI"
            ],
            "translate": false
        },
        "priya-system-monitor": {
            "path": "Priya.System.Monitor",
            "default": {
                "controller": "Priya.System.Monitor.run",
                "format": "html",
                "language": "en"
            },
            "method": [
                "GET",
                "POST"
            ],
            "translate": false
        },
        "priya-system-readline": {
            "path": "Priya.System.Readline",
            "default": {
                "controller": "Priya.System.Readline.run",
                "format": "html",
                "language": "en"
            },
            "method": [
                "GET",
                "POST"
            ],
            "translate": false
        },
        "priya-system-debug": {
            "path": "Priya.System.Debug",
            "default": {
                "controller": "Priya.System.Debug.run",
                "format": "html",
                "language": "en"
            },
            "method": [
                "GET",
                "POST"
            ],
            "translate": false
        },
        "priya-system-session": {
            "path": "Priya.System.Session",
            "default": {
                "controller": "Priya.System.Session.run",
                "format": "html",
                "language": "en"
            },
            "method": [
                "GET",
                "POST"
            ],
            "translate": false
        },
        "start": {
            "path": "",
            "default": {
                "controller": "Priya.Gui.run",
                "format": "html",
                "language": "en"
            },
            "method": [
                "GET",
                "POST"
            ],
            "translate": false
        },
        "priya-gui-user-login-process": {
            "path": "priya\/gui\/user\/login\/process",
            "default": {
                "controller": "Priya.Gui.User.Login.Process.run",
                "language": "en",
                "format": [
                    "html"
                ]
            },
            "translate": "false",
            "method": [
                "POST"
            ]
        },
        "priya-gui-user-login": {
            "path": "priya\/gui\/user\/login\/",
            "default": {
                "controller": "Priya.Gui.User.Login.run",
                "language": "en",
                "format": [
                    "html"
                ]
            },
            "translate": "false",
            "method": [
                "POST"
            ]
        },
        "priya-gui-user-logout": {
            "path": "priya\/gui\/user\/logout\/",
            "default": {
                "controller": "Priya.Gui.User.Login.Process.logout",
                "language": "en",
                "format": [
                    "html"
                ]
            },
            "translate": "false",
            "method": [
                "GET",
                "POST"
            ]
        },
        "priya-gui-install": {
            "path": "priya\/gui\/install\/",
            "default": {
                "controller": "Priya.Gui.Install.run",
                "language": "en",
                "format": [
                    "html"
                ]
            },
            "translate": "false",
            "method": [
                "GET",
                "POST"
            ]
        },
        "priya-gui-install-process": {
            "path": "priya\/gui\/install\/process\/",
            "default": {
                "controller": "Priya.Gui.Install.Process.run",
                "language": "en",
                "format": [
                    "html"
                ]
            },
            "translate": "false",
            "method": [
                "POST"
            ]
        },
        "priya-gui-navigation": {
            "path": "Priya.Gui.Navigation",
            "default": {
                "controller": "Priya.Gui.Navigation.run",
                "format": "html",
                "language": "en"
            },
            "method": [
                "GET",
                "POST"
            ],
            "translate": false
        },
        "priya-gui-font": {
            "path": "Priya.Gui.Font",
            "default": {
                "controller": "Priya.Gui.Font.run",
                "format": "html",
                "language": "en"
            },
            "method": [
                "GET",
                "POST"
            ],
            "translate": false
        },
        "priya-gui-error": {
            "path": "Priya.Gui.Error",
            "default": {
                "controller": "Priya.Gui.Message.Error.View.run",
                "format": "html",
                "language": "en"
            },
            "method": [
                "GET",
                "POST"
            ],
            "translate": false
        },
        "priya-gui-message": {
            "path": "Priya.Gui.Message",
            "default": {
                "controller": "Priya.Gui.Message.View.run",
                "format": "html",
                "language": "en"
            },
            "method": [
                "GET",
                "POST"
            ],
            "translate": false
        },
        "speak": {
            "path": "speak",
            "default": {
                "controller": "Speak.run",
                "format": "html",
                "language": "en"
            },
            "method": [
                "GET",
                "POST"
            ],
            "translate": false
        },
        "documentation-priya-software-main": {
            "path": "",
            "host": [
                "documentation.priya.software"
            ],
            "request": {
                "page": "Page",
                "document": "Introduction"
            },
            "controller": "Host.Documentation.Priya.Software.Page.document",
            "language": "en",
            "format": "html",
            "method": [
                "GET",
                "POST"
            ]
        },
        "documentation-priya-software-download": {
            "path": "Downloads\/",
            "host": [
                "documentation.priya.software"
            ],
            "url": "https:\/\/priya.software\/Downloads\/",
            "language": "en",
            "format": "html",
            "method": [
                "GET",
                "POST"
            ]
        },
        "documentation-priya-software-doxygen": {
            "path": "Doxygen\/",
            "host": [
                "documentation.priya.software"
            ],
            "url": "{$dir.host}Documentation\/Priya\/Software\/Public\/Doxygen\/classes.html",
            "language": "en",
            "format": "html",
            "method": [
                "GET",
                "POST"
            ]
        },
        "documentation-priya-software-document": {
            "path": "{$document}\/",
            "host": [
                "documentation.priya.software"
            ],
            "request": {
                "page": "Page"
            },
            "controller": "Host.Documentation.Priya.Software.Page.document",
            "language": "en",
            "format": "html",
            "method": [
                "GET",
                "POST"
            ]
        },
        "priya-software-main": {
            "path": "",
            "host": [
                "priya.software",
                "*.priya.software",
                "!documentation.priya.software"
            ],
            "request": {
                "page": "Home"
            },
            "controller": "Host.Priya.Software.Page.run",
            "language": "en",
            "format": "html",
            "method": [
                "GET",
                "POST"
            ]
        },
        "priya-software-menu": {
            "path": "Menu\/{$menu}",
            "host": [
                "priya.software",
                "*.priya.software",
                "!documentation.priya.software"
            ],
            "controller": "Host.Priya.Software.Menu.run",
            "language": "en",
            "format": "json",
            "method": [
                "GET",
                "POST"
            ]
        },
        "priya-software-page": {
            "path": "Page\/{$page}",
            "host": [
                "priya.software",
                "*.priya.software",
                "!documentation.priya.software"
            ],
            "controller": "Host.Priya.Software.Page.run",
            "language": "en",
            "format": "json",
            "method": [
                "GET",
                "POST"
            ]
        },
        "priya-software-download-url": {
            "path": "Download\/{$download}",
            "host": [
                "priya.software",
                "*.priya.software",
                "!documentation.priya.software"
            ],
            "url": "{$dir.host}Priya\/Software\/Public\/Download\/{$request.download}",
            "language": "en",
            "format": "json",
            "method": [
                "GET",
                "POST"
            ]
        },
        "priya-software-download": {
            "path": "Downloads",
            "host": [
                "priya.software",
                "*.priya.software",
                "!documentation.priya.software"
            ],
            "request": {
                "page": "Download"
            },
            "controller": "Host.Priya.Software.Page.run",
            "language": "en",
            "format": "json",
            "method": [
                "GET",
                "POST"
            ]
        },
        "priya-software-license": {
            "path": "License",
            "host": [
                "priya.software",
                "*.priya.software",
                "!documentation.priya.software"
            ],
            "url": "{$dir.host}Priya\/Software\/Public\/License",
            "language": "en",
            "format": "json",
            "method": [
                "GET",
                "POST"
            ]
        },
        "Host-Redirect-CLi": {
            "path": "Host\/Redirect",
            "controller": "Host.Redirect.Cli.run",
            "format": "html",
            "language": "en",
            "method": [
                "CLI"
            ],
            "translate": false
        },
        "like-it-cloud": {
            "request": {
                "host": "like-it.cloud"
            },
            "path": "",
            "host": [
                "like-it.cloud",
                "*.like-it.cloud"
            ],
            "controller": "Host.Redirect.run",
            "language": "en",
            "format": "html",
            "method": [
                "GET",
                "POST"
            ]
        },
        "like-it-cloud-page": {
            "request": {
                "host": "like-it.cloud"
            },
            "path": "\/{$page}",
            "host": [
                "like-it.cloud",
                "*.like-it.cloud"
            ],
            "controller": "Host.Redirect.run",
            "language": "en",
            "format": "html",
            "method": [
                "GET",
                "POST"
            ]
        },
        "newcom-app": {
            "path": "",
            "host": [
                "newcom.app",
                "*.newcom.app"
            ],
            "request": {
                "host": "newcom.app"
            },
            "controller": "Host.Redirect.run",
            "language": "en",
            "format": "html",
            "method": [
                "GET",
                "POST"
            ]
        },
        "newcom-app-page": {
            "path": "\/{$page}",
            "host": [
                "newcom.app",
                "*.newcom.app"
            ],
            "request": {
                "host": "newcom.app"
            },
            "controller": "Host.Redirect.run",
            "language": "en",
            "format": "html",
            "method": [
                "GET",
                "POST"
            ]
        },
        "priya-app": {
            "request": {
                "host": "priya.app"
            },
            "path": "",
            "host": [
                "priya.app",
                "*.priya.app",
                "!documentation.priya.app"
            ],
            "controller": "Host.Redirect.run",
            "language": "en",
            "format": "html",
            "method": [
                "GET",
                "POST"
            ]
        },
        "priya-app-page": {
            "request": {
                "host": "priya.app"
            },
            "path": "\/{$page}",
            "host": [
                "priya.app",
                "*.priya.app",
                "!documentation.priya.app"
            ],
            "controller": "Host.Redirect.run",
            "language": "en",
            "format": "html",
            "method": [
                "GET",
                "POST"
            ]
        },
        "alientrick-app": {
            "path": "",
            "host": [
                "alientrick.app",
                "*.alientrick.app"
            ],
            "request": {
                "host": "alientrick.app"
            },
            "controller": "Host.Redirect.run",
            "language": "en",
            "format": "html",
            "method": [
                "GET",
                "POST"
            ]
        },
        "alientrick-app-page": {
            "path": "\/{$page}",
            "host": [
                "alientrick.app",
                "*.alientrick.app"
            ],
            "request": {
                "host": "alientrick.app"
            },
            "controller": "Host.Redirect.run",
            "language": "en",
            "format": "html",
            "method": [
                "GET",
                "POST"
            ]
        },
        "lunchroom-app": {
            "path": "",
            "host": [
                "lunchroom.app",
                "*.lunchroom.app"
            ],
            "request": {
                "host": "lunchroom.app"
            },
            "controller": "Host.Redirect.run",
            "language": "en",
            "format": "html",
            "method": [
                "GET",
                "POST"
            ]
        },
        "lunchroom-app-page": {
            "path": "\/{$page}",
            "host": [
                "lunchroom.app",
                "*.lunchroom.app"
            ],
            "request": {
                "host": "lunchroom.app"
            },
            "controller": "Host.Redirect.run",
            "language": "en",
            "format": "html",
            "method": [
                "GET",
                "POST"
            ]
        },
        "funda-world": {
            "path": "",
            "host": [
                "funda.world",
                "*.funda.world"
            ],
            "request": {
                "host": "funda.world"
            },
            "controller": "Host.Redirect.run",
            "language": "en",
            "format": "html",
            "method": [
                "GET",
                "POST"
            ]
        },
        "funda-world-page": {
            "path": "\/{$page}",
            "host": [
                "funda.world",
                "*.funda.world"
            ],
            "request": {
                "host": "funda.world"
            },
            "controller": "Host.Redirect.run",
            "language": "en",
            "format": "html",
            "method": [
                "GET",
                "POST"
            ]
        },
        "enquete-app": {
            "request": {
                "host": "enquete.app"
            },
            "path": "",
            "host": [
                "enquete.app",
                "*.enquete.app"
            ],
            "controller": "Host.Redirect.run",
            "language": "en",
            "format": "html",
            "method": [
                "GET",
                "POST"
            ]
        },
        "enquete-app-page": {
            "request": {
                "host": "enquete.app"
            },
            "path": "\/{$page}",
            "host": [
                "enquete.app",
                "*.enquete.app"
            ],
            "controller": "Host.Redirect.run",
            "language": "en",
            "format": "html",
            "method": [
                "GET",
                "POST"
            ]
        },
        "esky-world": {
            "path": "",
            "host": [
                "esky.world",
                "*.esky.world"
            ],
            "request": {
                "host": "esky.world"
            },
            "controller": "Host.Redirect.run",
            "language": "en",
            "format": "html",
            "method": [
                "GET",
                "POST"
            ]
        },
        "esky-world-page": {
            "path": "\/{$page}",
            "host": [
                "esky.world",
                "*.esky.world"
            ],
            "request": {
                "host": "esky.world"
            },
            "controller": "Host.Redirect.run",
            "language": "en",
            "format": "html",
            "method": [
                "GET",
                "POST"
            ]
        },
        "exam-institute": {
            "path": "",
            "host": [
                "exam.institute",
                "*.exam.institute"
            ],
            "request": {
                "host": "exam.institute"
            },
            "controller": "Host.Redirect.run",
            "language": "en",
            "format": "html",
            "method": [
                "GET",
                "POST"
            ]
        },
        "exam-institute-page": {
            "path": "\/{$page}",
            "host": [
                "exam.institute",
                "*.exam.institute"
            ],
            "request": {
                "host": "exam.institute"
            },
            "controller": "Host.Redirect.run",
            "language": "en",
            "format": "html",
            "method": [
                "GET",
                "POST"
            ]
        },
        "exams-world": {
            "path": "",
            "host": [
                "exams.world",
                "*.exams.world"
            ],
            "request": {
                "host": "exams.world"
            },
            "controller": "Host.Redirect.run",
            "language": "en",
            "format": "html",
            "method": [
                "GET",
                "POST"
            ]
        },
        "exams-world-page": {
            "path": "\/{$page}",
            "host": [
                "exams.world",
                "*.exams.world"
            ],
            "request": {
                "host": "exams.world"
            },
            "controller": "Host.Redirect.run",
            "language": "en",
            "format": "html",
            "method": [
                "GET",
                "POST"
            ]
        },
        "fuck-nose-world": {
            "request": {
                "host": "fuck-nose.world"
            },
            "path": "",
            "host": [
                "fuck-nose.world",
                "*.fuck-nose.world"
            ],
            "controller": "Host.Redirect.run",
            "language": "en",
            "format": "html",
            "method": [
                "GET",
                "POST"
            ]
        },
        "fuck-nose-world-page": {
            "request": {
                "host": "fuck-nose.world"
            },
            "path": "\/{$page}",
            "host": [
                "fuck-nose.world",
                "*.fuck-nose.world"
            ],
            "controller": "Host.Redirect.run",
            "language": "en",
            "format": "html",
            "method": [
                "GET",
                "POST"
            ]
        },
        "fuck-knows-app": {
            "path": "",
            "host": [
                "fuck-knows.app",
                "*.fuck-knows.app"
            ],
            "request": {
                "host": "fuck-knows.app"
            },
            "controller": "Host.Redirect.run",
            "language": "en",
            "format": "html",
            "method": [
                "GET",
                "POST"
            ]
        },
        "fuck-knows-app-page": {
            "path": "\/{$page}",
            "host": [
                "fuck-knows.app",
                "*.fuck-knows.app"
            ],
            "request": {
                "host": "fuck-knows.app"
            },
            "controller": "Host.Redirect.run",
            "language": "en",
            "format": "html",
            "method": [
                "GET",
                "POST"
            ]
        },
        "like-it-app": {
            "path": "",
            "host": [
                "like-it.app",
                "*.like-it.app"
            ],
            "request": {
                "host": "like-it.app"
            },
            "controller": "Host.Redirect.run",
            "language": "en",
            "format": "html",
            "method": [
                "GET",
                "POST"
            ]
        },
        "like-it-app-page": {
            "path": "\/{$page}",
            "host": [
                "like-it.app",
                "*.like-it.app"
            ],
            "request": {
                "host": "like-it.app"
            },
            "controller": "Host.Redirect.run",
            "language": "en",
            "format": "html",
            "method": [
                "GET",
                "POST"
            ]
        },
        "love-it-app": {
            "path": "",
            "host": [
                "love-it.app",
                "*.love-it.app"
            ],
            "request": {
                "host": "love-it.app"
            },
            "controller": "Host.Redirect.run",
            "language": "en",
            "format": "html",
            "method": [
                "GET",
                "POST"
            ]
        },
        "love-it-app-page": {
            "path": "\/{$page}",
            "host": [
                "love-it.app",
                "*.love-it.app"
            ],
            "request": {
                "host": "love-it.app"
            },
            "controller": "Host.Redirect.run",
            "language": "en",
            "format": "html",
            "method": [
                "GET",
                "POST"
            ]
        },
        "mydate-world": {
            "path": "",
            "host": [
                "mydate.world",
                "*.mydate.world"
            ],
            "request": {
                "host": "mydate.world"
            },
            "controller": "Host.Redirect.run",
            "language": "en",
            "format": "html",
            "method": [
                "GET",
                "POST"
            ]
        },
        "mydate-world-page": {
            "path": "\/{$page}",
            "host": [
                "mydate.world",
                "*.mydate.world"
            ],
            "request": {
                "host": "mydate.world"
            },
            "controller": "Host.Redirect.run",
            "language": "en",
            "format": "html",
            "method": [
                "GET",
                "POST"
            ]
        },
        "onderzoek-app": {
            "path": "",
            "host": [
                "onderzoek.app",
                "*.onderzoek.app"
            ],
            "request": {
                "host": "onderzoek.app"
            },
            "controller": "Host.Redirect.run",
            "language": "en",
            "format": "html",
            "method": [
                "GET",
                "POST"
            ]
        },
        "onderzoek-app-page": {
            "path": "\/{$page}",
            "host": [
                "onderzoek.app",
                "*.onderzoek.app"
            ],
            "request": {
                "host": "onderzoek.app"
            },
            "controller": "Host.Redirect.run",
            "language": "en",
            "format": "html",
            "method": [
                "GET",
                "POST"
            ]
        },
        "rime-app": {
            "path": "",
            "host": [
                "rime.app",
                "*.rime.app"
            ],
            "request": {
                "host": "rime.app"
            },
            "controller": "Host.Redirect.run",
            "language": "en",
            "format": "html",
            "method": [
                "GET",
                "POST"
            ]
        },
        "rime-app-page": {
            "path": "\/{$page}",
            "host": [
                "rime.app",
                "*.rime.app"
            ],
            "request": {
                "host": "rime.app"
            },
            "controller": "Host.Redirect.run",
            "language": "en",
            "format": "html",
            "method": [
                "GET",
                "POST"
            ]
        },
        "send-message-app": {
            "path": "",
            "host": [
                "send-message.app",
                "*.send-message.app"
            ],
            "request": {
                "host": "send-message.app"
            },
            "controller": "Host.Redirect.run",
            "language": "en",
            "format": "html",
            "method": [
                "GET",
                "POST"
            ]
        },
        "send-message-app-page": {
            "path": "\/{$page}",
            "host": [
                "send-message.app",
                "*.send-message.app"
            ],
            "request": {
                "host": "send-message.app"
            },
            "controller": "Host.Redirect.run",
            "language": "en",
            "format": "html",
            "method": [
                "GET",
                "POST"
            ]
        },
        "smart-contract-cloud": {
            "path": "",
            "host": [
                "smart-contract.cloud",
                "*.smart-contract.cloud"
            ],
            "request": {
                "host": "smart-contract.cloud"
            },
            "controller": "Host.Redirect.run",
            "language": "en",
            "format": "html",
            "method": [
                "GET",
                "POST"
            ]
        },
        "smart-contract-cloud-page": {
            "path": "\/{$page}",
            "host": [
                "smart-contract.cloud",
                "*.smart-contract.cloud"
            ],
            "request": {
                "host": "smart-contract.cloud"
            },
            "controller": "Host.Redirect.run",
            "language": "en",
            "format": "html",
            "method": [
                "GET",
                "POST"
            ]
        },
        "smart-contract-software": {
            "path": "",
            "host": [
                "smart-contract.software",
                "*.smart-contract.software"
            ],
            "request": {
                "host": "smart-contract.software"
            },
            "controller": "Host.Redirect.run",
            "language": "en",
            "format": "html",
            "method": [
                "GET",
                "POST"
            ]
        },
        "smart-contract-software-page": {
            "path": "\/{$page}",
            "host": [
                "smart-contract.software",
                "*.smart-contract.software"
            ],
            "request": {
                "host": "smart-contract.software"
            },
            "controller": "Host.Redirect.run",
            "language": "en",
            "format": "html",
            "method": [
                "GET",
                "POST"
            ]
        },
        "webprint-app": {
            "path": "",
            "host": [
                "webprint.app",
                "*.webprint.app"
            ],
            "request": {
                "host": "webprint.app"
            },
            "controller": "Host.Redirect.run",
            "language": "en",
            "format": "html",
            "method": [
                "GET",
                "POST"
            ]
        },
        "webprint-app-page": {
            "path": "\/{$page}",
            "host": [
                "webprint.app",
                "*.webprint.app"
            ],
            "request": {
                "host": "webprint.app"
            },
            "controller": "Host.Redirect.run",
            "language": "en",
            "format": "html",
            "method": [
                "GET",
                "POST"
            ]
        },
        "app-issue": {
            "path": "app\/issue",
            "controller": "App.Issue.Main.run",
            "language": "en",
            "format": [
                "json"
            ],
            "translate": "false",
            "method": [
                "GET",
                "POST"
            ]
        },
        "app-issue-overview-sortable": {
            "path": "app\/issue\/overview\/sortable",
            "controller": "App.Issue.Overview.sortable",
            "language": "en",
            "format": [
                "json"
            ],
            "translate": "false",
            "method": [
                "POST"
            ]
        },
        "app-issue-overview-sort-up": {
            "path": "app\/issue\/overview\/sort-up\/{$page}",
            "controller": "App.Issue.Overview.sortUp",
            "language": "en",
            "format": [
                "json"
            ],
            "translate": "false",
            "method": [
                "POST"
            ]
        },
        "app-issue-overview-sort-down": {
            "path": "app\/issue\/overview\/sort-down\/{$page}",
            "controller": "App.Issue.Overview.sortDown",
            "language": "en",
            "format": [
                "json"
            ],
            "translate": "false",
            "method": [
                "POST"
            ]
        },
        "app-issue-overview-contextmenu": {
            "path": "app\/issue\/overview\/contextmenu\/{$page}",
            "controller": "App.Issue.Overview.contextMenu",
            "format": "html",
            "language": "en",
            "method": [
                "GET",
                "POST"
            ],
            "translate": false
        },
        "app-issue-overview": {
            "path": "app\/issue\/overview\/{$page}",
            "controller": "App.Issue.Overview.run",
            "format": "html",
            "language": "en",
            "method": [
                "GET",
                "POST"
            ],
            "translate": false
        },
        "app-issue-search": {
            "path": "app\/issue\/search\/{$page}",
            "controller": "App.Issue.Overview.run",
            "format": "html",
            "language": "en",
            "method": [
                "GET",
                "POST"
            ],
            "translate": false
        },
        "app-issue-filter": {
            "path": "app\/issue\/filter\/{$page}",
            "controller": "App.Issue.Overview.run",
            "format": "html",
            "language": "en",
            "method": [
                "GET",
                "POST"
            ],
            "translate": false
        },
        "app-issue-setting": {
            "path": "app\/issue\/setting\/",
            "controller": "App.Issue.Setting.run",
            "format": "html",
            "language": "en",
            "method": [
                "GET",
                "POST"
            ],
            "translate": false
        },
        "app-issue-setting-process": {
            "path": "app\/issue\/setting\/process\/",
            "controller": "App.Issue.Process.setting",
            "format": "html",
            "language": "en",
            "method": [
                "POST"
            ],
            "translate": false
        },
        "app-issue-list": {
            "path": "app\/issue\/list\/",
            "controller": "App.Issue.NodeList.run",
            "format": "html",
            "language": "en",
            "method": [
                "GET",
                "POST"
            ],
            "translate": false
        },
        "app-issue-detail": {
            "path": "app\/issue\/detail\/{$jid}\/",
            "controller": "App.Issue.Detail.run",
            "format": "json",
            "language": "en",
            "method": [
                "GET",
                "POST"
            ],
            "translate": false
        },
        "app-issue-message": {
            "path": "app\/issue\/message\/{$action}\/",
            "controller": "App.Issue.Message.run",
            "format": "html",
            "language": "en",
            "method": [
                "GET",
                "POST"
            ],
            "translate": false
        },
        "app-issue-process": {
            "path": "app\/issue\/process\/",
            "controller": "App.Issue.Process.run",
            "language": "en",
            "format": [
                "json"
            ],
            "translate": "false",
            "method": [
                "POST"
            ]
        },
        "app-issue-process-close": {
            "path": "app\/issue\/process\/close\/{$jid}\/{$page}",
            "controller": "App.Issue.Process.close",
            "format": "html",
            "language": "en",
            "method": [
                "GET",
                "POST"
            ],
            "translate": false
        },
        "app-issue-process-re-open": {
            "path": "app\/issue\/process\/re-open\/{$jid}",
            "controller": "App.Issue.Process.reOpen",
            "format": "html",
            "language": "en",
            "method": [
                "GET",
                "POST"
            ],
            "translate": false
        },
        "app-issue-process-delete": {
            "path": "app\/issue\/process\/delete\/{$jid}",
            "controller": "App.Issue.Process.delete",
            "format": "html",
            "language": "en",
            "method": [
                "GET",
                "POST"
            ],
            "translate": false
        },
        "app-issue-process-restore": {
            "path": "app\/issue\/process\/restore\/{$jid}",
            "controller": "App.Issue.Process.restore",
            "format": "html",
            "language": "en",
            "method": [
                "GET",
                "POST"
            ],
            "translate": false
        },
        "app-issue-delete": {
            "path": "app\/issue\/delete\/{$jid}\/",
            "controller": "App.Issue.Delete.run",
            "language": "en",
            "format": [
                "html",
                " json"
            ],
            "translate": "false",
            "method": [
                "GET",
                "POST"
            ]
        },
        "app-issue-label-detail": {
            "path": "app\/issue\/label\/detail\/{$jid}\/",
            "controller": "App.Issue.Label.Detail.run",
            "format": "html",
            "language": "en",
            "method": [
                "GET",
                "POST"
            ],
            "translate": false
        },
        "app-issue-label-process": {
            "path": "app\/issue\/label\/process\/",
            "controller": "App.Issue.Label.Process.run",
            "format": "html",
            "language": "en",
            "method": [
                "GET",
                "POST"
            ],
            "translate": false
        },
        "app-issue-label-overview": {
            "path": "app\/issue\/label\/overview\/",
            "controller": "App.Issue.Label.Overview.run",
            "format": "html",
            "language": "en",
            "method": [
                "GET",
                "POST"
            ],
            "translate": false
        },
        "app-issue-label-process-delete": {
            "path": "app\/issue\/label\/delete\/{$jid}\/",
            "controller": "App.Issue.Label.Process.delete",
            "language": "en",
            "format": [
                "html",
                "json"
            ],
            "translate": "false",
            "method": [
                "GET",
                "POST"
            ]
        },
        "app-file-manager": {
            "path": "app\/file\/manager",
            "controller": "App.File.Manager.Main.run",
            "language": "en",
            "format": [
                "json"
            ],
            "translate": "false",
            "method": [
                "GET",
                "POST"
            ]
        },
        "app-file-manager-nodelist": {
            "path": "app\/file\/manager\/nodelist\/{$dir}",
            "controller": "App.File.Manager.Nodelist.run",
            "language": "en",
            "format": [
                "json"
            ],
            "translate": "false",
            "method": [
                "GET",
                "POST"
            ]
        },
        "app-file-manager-rename": {
            "path": "app\/file\/manager\/rename",
            "controller": "App.File.Manager.Rename.run",
            "language": "en",
            "format": [
                "json"
            ],
            "translate": "false",
            "method": [
                "GET",
                "POST"
            ]
        },
        "app-file-manager-open": {
            "path": "app\/file\/manager\/open",
            "controller": "App.File.Manager.Open.run",
            "language": "en",
            "format": [
                "json"
            ],
            "translate": "false",
            "method": [
                "GET",
                "POST"
            ]
        },
        "app-file-manager-process-open": {
            "path": "app\/file\/manager\/process\/open",
            "controller": "App.File.Manager.Process.open",
            "language": "en",
            "format": [
                "json"
            ],
            "translate": "false",
            "method": [
                "GET",
                "POST"
            ]
        },
        "app-file-manager-overview": {
            "path": "app\/file\/manager\/overview",
            "controller": "App.File.Manager.Overview.run",
            "language": "en",
            "format": [
                "json"
            ],
            "translate": "false",
            "method": [
                "GET",
                "POST"
            ]
        },
        "app-file-manager-tree": {
            "path": "app\/file\/manager\/tree\/{$dir}",
            "controller": "App.File.Manager.Tree.run",
            "language": "en",
            "format": [
                "json"
            ],
            "translate": "false",
            "method": [
                "GET",
                "POST"
            ]
        },
        "app-file-manager-expand": {
            "path": "app\/file\/manager\/expand\/{$dir}",
            "controller": "App.File.Manager.Expand.run",
            "language": "en",
            "format": [
                "json"
            ],
            "translate": "false",
            "method": [
                "GET",
                "POST"
            ]
        },
        "app-file-manager-upload": {
            "path": "app\/file\/manager\/upload\/",
            "controller": "App.File.Manager.Process.upload",
            "language": "en",
            "format": [
                "json"
            ],
            "translate": "false",
            "method": [
                "GET",
                "POST"
            ]
        },
        "app-audio-player": {
            "path": "Audio\/Player",
            "default": {
                "controller": "App.Audio.Player.Main.run",
                "language": "en",
                "format": [
                    "json"
                ]
            },
            "translate": "false",
            "method": [
                "GET",
                "POST"
            ]
        },
        "app-audio-player-run": {
            "path": "Audio\/Player\/Run\/{$file}",
            "default": {
                "controller": "App.Audio.Player.Run.run",
                "language": "en",
                "format": [
                    "json"
                ]
            },
            "translate": "false",
            "method": [
                "GET",
                "POST"
            ]
        },
        "app-audio-player-id3": {
            "path": "Audio\/Player\/Id3\/{$file}",
            "default": {
                "controller": "App.Audio.Player.Id3.run",
                "language": "en",
                "format": [
                    "json"
                ]
            },
            "translate": "false",
            "method": [
                "GET",
                "POST"
            ]
        },
        "app-youtube": {
            "path": "Youtube",
            "default": {
                "controller": "App.Youtube.Main.run",
                "language": "en",
                "format": [
                    "json"
                ]
            },
            "translate": "false",
            "method": [
                "GET",
                "POST"
            ]
        },
        "app-youtube-iframe": {
            "path": "Youtube\/Iframe",
            "default": {
                "controller": "App.Youtube.Iframe.run",
                "language": "en",
                "format": [
                    "json"
                ]
            },
            "translate": "false",
            "method": [
                "GET",
                "POST"
            ]
        },
        "app-youtube-download": {
            "path": "Youtube\/Download",
            "default": {
                "controller": "App.Youtube.Download.run",
                "language": "en",
                "format": [
                    "json"
                ]
            },
            "translate": "false",
            "method": [
                "GET",
                "POST"
            ]
        },
        "app-youtube-search": {
            "path": "Youtube\/Search",
            "default": {
                "controller": "App.Youtube.Search.run",
                "language": "en",
                "format": [
                    "json"
                ]
            },
            "translate": "false",
            "method": [
                "GET",
                "POST"
            ]
        },
        "app-youtube-process-download": {
            "path": "Youtube\/Process\/download\/{$url}",
            "default": {
                "controller": "App.Youtube.Process.download",
                "language": "en",
                "format": [
                    "json"
                ]
            },
            "translate": "false",
            "method": [
                "GET",
                "POST"
            ]
        },
        "app-youtube-process-monitor": {
            "path": "Youtube\/Process\/Monitor\/{$url}",
            "default": {
                "controller": "App.Youtube.Process.monitor",
                "language": "en",
                "format": [
                    "json"
                ]
            },
            "translate": "false",
            "method": [
                "GET",
                "POST"
            ]
        },
        "app-youtube-process": {
            "path": "Youtube\/Process\/{$url}",
            "default": {
                "controller": "App.Youtube.Process.run",
                "language": "en",
                "format": [
                    "json"
                ]
            },
            "translate": "false",
            "method": [
                "GET",
                "POST"
            ]
        },
        "application-copyright": {
            "path": "Application\/Copyright\/",
            "controller": "Priya.Module.Cli.Application.Copyright.run",
            "method": [
                "CLI"
            ],
            "translate": false
        },
        "copyright-shorthand": {
            "path": "Copyright\/",
            "controller": "Priya.Module.Cli.Application.Copyright.run",
            "method": [
                "CLI"
            ],
            "translate": false
        },
        "application-version": {
            "path": "Application\/Version\/",
            "controller": "Priya.Module.Cli.Application.Version.run",
            "method": [
                "CLI"
            ],
            "translate": false
        },
        "version-shorthand": {
            "path": "Version\/",
            "controller": "Priya.Module.Cli.Application.Version.run",
            "method": [
                "CLI"
            ],
            "translate": false
        },
        "application-license": {
            "path": "Application\/License\/",
            "controller": "Priya.Module.Cli.Application.License.run",
            "method": [
                "CLI"
            ],
            "translate": false
        },
        "license-shorthand": {
            "path": "License\/",
            "controller": "Priya.Module.Cli.Application.License.run",
            "method": [
                "CLI"
            ],
            "translate": false
        },
        "application-bin": {
            "path": "Application\/Bin\/",
            "controller": "Priya.Module.Cli.Application.Bin.run",
            "method": [
                "CLI"
            ],
            "translate": false
        },
        "bin-shorthand": {
            "path": "Bin\/",
            "controller": "Priya.Module.Cli.Application.Bin.run",
            "method": [
                "CLI"
            ],
            "translate": false
        },
        "application-locate": {
            "path": "Application\/Locate\/",
            "controller": "Priya.Module.Cli.Application.Locate.run",
            "method": [
                "CLI"
            ],
            "translate": false
        },
        "locate-shorthand": {
            "path": "Locate\/",
            "controller": "Priya.Module.Cli.Application.Locate.run",
            "method": [
                "CLI"
            ],
            "translate": false
        },
        "application-config": {
            "path": "Application\/Config\/",
            "controller": "Priya.Module.Cli.Application.Config.run",
            "method": [
                "CLI"
            ],
            "translate": false
        },
        "config-shorthand": {
            "path": "Config\/",
            "controller": "Priya.Module.Cli.Application.Config.run",
            "method": [
                "CLI"
            ],
            "translate": false
        },
        "application-help": {
            "path": "Application\/Help\/",
            "controller": "Priya.Module.Cli.Application.Help.run",
            "method": [
                "CLI"
            ],
            "translate": false
        },
        "help-shorthand": {
            "path": "Help\/",
            "controller": "Priya.Module.Cli.Application.Help.run",
            "method": [
                "CLI"
            ],
            "translate": false
        },
        "application-error": {
            "path": "Application\/Error\/",
            "controller": "Priya.Module.Cli.Application.Error.run",
            "method": [
                "CLI"
            ],
            "translate": false
        },
        "error-shorthand": {
            "path": "Error\/",
            "controller": "Priya.Module.Cli.Application.Error.run",
            "method": [
                "CLI"
            ],
            "translate": false
        },
        "application-route": {
            "path": "Application\/Route\/",
            "controller": "Priya.Module.Cli.Application.Route.run",
            "method": [
                "CLI"
            ],
            "translate": false
        },
        "route-shorthand": {
            "path": "Route\/",
            "controller": "Priya.Module.Cli.Application.Route.run",
            "method": [
                "CLI"
            ],
            "translate": false
        },
        "application-parser": {
            "path": "Application\/Parser\/",
            "controller": "Priya.Module.Cli.Application.Parser.run",
            "method": [
                "CLI"
            ],
            "translate": false
        },
        "parser-shorthand": {
            "path": "Parser\/",
            "controller": "Priya.Module.Cli.Application.Parser.run",
            "method": [
                "CLI"
            ],
            "translate": false
        },
        "application-cache": {
            "path": "Application\/Cache\/",
            "controller": "Priya.Module.Cli.Application.Cache.run",
            "method": [
                "CLI"
            ],
            "translate": false
        },
        "cache-shorthand": {
            "path": "Cache\/",
            "controller": "Priya.Module.Cli.Application.Cache.run",
            "method": [
                "CLI"
            ],
            "translate": false
        },
        "application-task": {
            "path": "Application\/Task\/",
            "controller": "Priya.Module.Cli.Application.Task.run",
            "method": [
                "CLI"
            ],
            "translate": false
        },
        "task-shorthand": {
            "path": "Task\/",
            "controller": "Priya.Module.Cli.Application.Task.run",
            "method": [
                "CLI"
            ],
            "translate": false
        },
        "application-host": {
            "path": "Application\/Host\/",
            "controller": "Priya.Module.Cli.Application.Host.run",
            "method": [
                "CLI"
            ],
            "translate": false
        },
        "host-shorthand": {
            "path": "Host\/",
            "controller": "Priya.Module.Cli.Application.Host.run",
            "method": [
                "CLI"
            ],
            "translate": false
        },
        "test": {
            "path": "Test\/",
            "controller": "Priya.Module.Cli.Test.run",
            "method": [
                "CLI"
            ],
            "translate": false
        }
    }
}