{
    "@see": "http:\/\/documentation.priya.software\/Javascript\/Bootstrap",
    "name": "Javascript",
    "core": "Bin\/",
    "prototype": "",
    "extension": ".js",
    "query": "0.3.12",
    "collect": {
        "version": "0.3.12",
        "expose": {
            "namespace": "_",
            "require": "require",
            "window": {
                "isset": "isset",
                "empty": "empty",
                "microtime": "microtime",
                "trim": "trim",
                "run": "run",
                "select": "select",
                "get": "get",
                "request": "request",
                "attach": "attach"
            }
        }
    },
    "require": {
        "core": [
            "Bin\/Core-0.3.12.js?0.3.12"
        ]
    }
}